yesno/__init__.py
yesno.wtf-0.0.1.dist-info/LICENSE
yesno.wtf-0.0.1.dist-info/METADATA
yesno.wtf-0.0.1.dist-info/WHEEL
yesno.wtf-0.0.1.dist-info/top_level.txt
yesno.wtf-0.0.1.dist-info/RECORD
