Metadata-Version: 2.1
Name: yesno.wtf
Version: 0.0.1
Summary: Wrapper for yesno.wtf
Home-page: https://github.com/Nemupy/yesno.wtf
Author: Nemupy
Author-email: nemu.otoyume@gmail.com
License-File: LICENSE
